odoo/addons/sale_partner_address_restrict/README.rst
odoo/addons/sale_partner_address_restrict/__init__.py
odoo/addons/sale_partner_address_restrict/__manifest__.py
odoo/addons/sale_partner_address_restrict/i18n/it.po
odoo/addons/sale_partner_address_restrict/i18n/sale_partner_address_restrict.pot
odoo/addons/sale_partner_address_restrict/models/__init__.py
odoo/addons/sale_partner_address_restrict/models/res_company.py
odoo/addons/sale_partner_address_restrict/models/res_config_settings.py
odoo/addons/sale_partner_address_restrict/models/res_partner.py
odoo/addons/sale_partner_address_restrict/models/sale_order.py
odoo/addons/sale_partner_address_restrict/readme/CONFIGURE.md
odoo/addons/sale_partner_address_restrict/readme/CONTRIBUTORS.md
odoo/addons/sale_partner_address_restrict/readme/DESCRIPTION.md
odoo/addons/sale_partner_address_restrict/static/description/icon.png
odoo/addons/sale_partner_address_restrict/static/description/index.html
odoo/addons/sale_partner_address_restrict/tests/__init__.py
odoo/addons/sale_partner_address_restrict/tests/test_sale_order.py
odoo/addons/sale_partner_address_restrict/views/res_config_settings.xml
odoo/addons/sale_partner_address_restrict/views/res_partner_views.xml
odoo/addons/sale_partner_address_restrict/views/sale_order_view.xml
odoo_addon_sale_partner_address_restrict-18.0.1.0.0.5.dist-info/METADATA
odoo_addon_sale_partner_address_restrict-18.0.1.0.0.5.dist-info/WHEEL
odoo_addon_sale_partner_address_restrict-18.0.1.0.0.5.dist-info/top_level.txt
odoo_addon_sale_partner_address_restrict-18.0.1.0.0.5.dist-info/RECORD
