Metadata-Version: 2.1
Name: odoo-addon-sale_partner_address_restrict
Version: 18.0.1.0.0.5
Requires-Python: >=3.10
Requires-Dist: odoo-addon-base_partition==18.0.*
Requires-Dist: odoo==18.0.*
Summary: Restrict addresses domain in the sales order form taking into account the partner selected
Home-page: https://github.com/OCA/sale-workflow
License: AGPL-3
Author: ForgeFlow, Odoo Community Association (OCA)
Author-email: support@odoo-community.org
Classifier: Programming Language :: Python
Classifier: Framework :: Odoo
Classifier: Framework :: Odoo :: 18.0
Classifier: License :: OSI Approved :: GNU Affero General Public License v3
